PyWDCKit/__init__.py
PyWDCKit/main.py
PyWDCKit-1.0.0.3.dist-info/LICENSE
PyWDCKit-1.0.0.3.dist-info/METADATA
PyWDCKit-1.0.0.3.dist-info/WHEEL
PyWDCKit-1.0.0.3.dist-info/top_level.txt
PyWDCKit-1.0.0.3.dist-info/RECORD
