Metadata-Version: 2.1
Name: PyWDCKit
Version: 1.0.0.3
Summary: UNOFFICIAL Python bindings for Western Digital's WDCKit drive utility
Home-page: https://github.com/mohamed-fazal-wdc/lib_wdckit
Author: mohamed-fazal-wdc (Mohamed Farhan Fazal)
Author-email: mohamed.fazal@wdc.com
Project-URL: Bug Tracker, https://github.com/mohamed-fazal-wdc/lib_wdckit/issues
Keywords: python,wdckit,Western Digital,Sandisk,NVMe,SATA,NVMe M.2,SSD,HDD
Classifier: Development Status :: 5 - Production/Stable
Classifier: Intended Audience :: Developers
Classifier: Programming Language :: Python :: 3
Classifier: Operating System :: Microsoft :: Windows
Classifier: License :: Freeware
License-File: LICENSE
Requires-Dist: pywin32
